<?xml version="1.0" encoding="UTF-8"?>
<beans xmlns="http://www.springframework.org/schema/beans"
	xmlns:xsi="http://www.w3.org/2001/XMLSchema-instance" xmlns:p="http://www.springframework.org/schema/p"
	xmlns:context="http://www.springframework.org/schema/context"
	xmlns:aop="http://www.springframework.org/schema/aop" xmlns:mvc="http://www.springframework.org/schema/mvc"
	xsi:schemaLocation="http://www.springframework.org/schema/mvc
           http://www.springframework.org/schema/mvc/spring-mvc.xsd
		   http://www.springframework.org/schema/beans http://www.springframework.org/schema/beans/spring-beans.xsd
           http://www.springframework.org/schema/aop  http://www.springframework.org/schema/aop/spring-aop.xsd
           http://www.springframework.org/schema/context http://www.springframework.org/schema/context/spring-context.xsd">

	<context:component-scan
		base-package="conddb.dao.svc,conddb.dao.admin,conddb.dao.controllers,conddb.dao.repositories" />
	<!-- Services -->
	<bean id="globalTagAdminController" class="conddb.dao.admin.controllers.GlobalTagAdminController" />
	<bean id="globalTagController" class="conddb.dao.controllers.GlobalTagController" />
	<bean id="iovController" class="conddb.dao.controllers.IovController" />
	<bean id="conddbClientService" class="conddb.dao.svc.ConddbClientService" />
	<bean id="profilingAdvisor" class="conddb.utils.aop.ProfilingAdvisor"></bean>
	<bean id="profilingMethodInterceptor" class="conddb.utils.aop.ProfilingMethodInterceptor"></bean>

	<!-- this is the actual advice itself -->
	<bean id="profilingAspect" class="conddb.utils.aop.ProfilingAspect" />

	<aop:config>
		<aop:aspect ref="profilingAspect">
			<aop:pointcut id="getGlobalTagTrace"
				expression="execution(* conddb.dao.svc.ConddbClientService.getGlobalTagTrace(String))
                    and args(logAction)" />

			<aop:around pointcut-ref="getGlobalTagTrace" method="logAction" />

		</aop:aspect>
	</aop:config>

	<bean id="taskExecutor"
		class="org.springframework.scheduling.concurrent.ThreadPoolTaskExecutor">
		<property name="corePoolSize" value="5" />
		<property name="maxPoolSize" value="10" />
		<property name="queueCapacity" value="25" />
	</bean>

<!-- 			<bean -->
<!-- 				class="org.springframework.web.servlet.mvc.method.annotation.RequestMappingHandlerAdapter"> -->
<!-- 				<property name="messageConverters"> -->
<!-- 					<list> -->
<!-- 						<ref bean="jsonConverter" /> -->
<!-- 					</list> -->
<!-- 				</property> -->
<!-- 			</bean> -->

<!-- 	<mvc:annotation-driven> -->
<!-- 		<mvc:message-converters> -->

<!-- 			<bean id="jsonConverter" -->
<!-- 				class="org.springframework.http.converter.json.MappingJackson2HttpMessageConverter"> -->
<!-- 				<property name="supportedMediaTypes" value="application/json" /> -->
<!-- 				<property name="objectMapper"> -->
<!-- 					<bean class="conddb.utils.json.HibernateAwareObjectMapper" /> -->
<!-- 				</property> -->
<!-- 			</bean> -->
<!-- 		</mvc:message-converters> -->
<!-- 	</mvc:annotation-driven> -->
</beans>